{
  "topicSlug": "astro",
  "title": "astro",
  "repo": "withastro/astro",
  "pageCount": 10,
  "locales": {
    "en": {
      "label": "English",
      "basePath": "/en/astro/"
    },
    "zh": {
      "label": "简体中文",
      "basePath": "/zh/astro/"
    }
  },
  "pages": [
    {
      "slug": "index",
      "title": "Overview",
      "navTitle": "Overview",
      "order": 1,
      "purpose": "What the project does, who it is for, and when to use it.",
      "targetKeywords": [
        "astro overview",
        "astro tutorial",
        "astro documentation"
      ]
    },
    {
      "slug": "getting-started",
      "title": "Getting Started",
      "navTitle": "Getting Started",
      "order": 2,
      "purpose": "Install the project and complete the first useful workflow.",
      "targetKeywords": [
        "astro getting started",
        "astro tutorial",
        "astro documentation"
      ]
    },
    {
      "slug": "core-concepts",
      "title": "Core Concepts",
      "navTitle": "Core Concepts",
      "order": 3,
      "purpose": "Explain the vocabulary and mental model behind the project.",
      "targetKeywords": [
        "astro core concepts",
        "astro tutorial",
        "astro documentation"
      ]
    },
    {
      "slug": "installation",
      "title": "Installation",
      "navTitle": "Installation",
      "order": 4,
      "purpose": "Cover supported runtimes, package managers, and environment setup.",
      "targetKeywords": [
        "astro installation",
        "astro tutorial",
        "astro documentation"
      ]
    },
    {
      "slug": "configuration",
      "title": "Configuration",
      "navTitle": "Configuration",
      "order": 5,
      "purpose": "Document configuration files, flags, and common presets.",
      "targetKeywords": [
        "astro configuration",
        "astro tutorial",
        "astro documentation"
      ]
    },
    {
      "slug": "tutorials",
      "title": "Tutorials",
      "navTitle": "Tutorials",
      "order": 6,
      "purpose": "Walk through practical tasks from beginner to intermediate level.",
      "targetKeywords": [
        "astro tutorials",
        "astro tutorial",
        "astro documentation"
      ]
    },
    {
      "slug": "examples",
      "title": "Examples",
      "navTitle": "Examples",
      "order": 7,
      "purpose": "Collect realistic examples readers can adapt.",
      "targetKeywords": [
        "astro examples",
        "astro tutorial",
        "astro documentation"
      ]
    },
    {
      "slug": "comparisons",
      "title": "Comparisons",
      "navTitle": "Comparisons",
      "order": 8,
      "purpose": "Compare alternatives and explain selection tradeoffs.",
      "targetKeywords": [
        "astro comparisons",
        "astro tutorial",
        "astro documentation"
      ]
    },
    {
      "slug": "faq",
      "title": "FAQ",
      "navTitle": "FAQ",
      "order": 9,
      "purpose": "Answer common adoption, migration, and troubleshooting questions.",
      "targetKeywords": [
        "astro faq",
        "astro tutorial",
        "astro documentation"
      ]
    },
    {
      "slug": "resources",
      "title": "Resources",
      "navTitle": "Resources",
      "order": 10,
      "purpose": "Link official docs, releases, examples, and source references.",
      "targetKeywords": [
        "astro resources",
        "astro tutorial",
        "astro documentation"
      ]
    }
  ],
  "translations": {
    "zh": [
      {
        "slug": "index",
        "title": "概览",
        "navTitle": "概览",
        "order": 1,
        "purpose": "What the project does, who it is for, and when to use it.",
        "targetKeywords": [
          "astro overview",
          "astro tutorial",
          "astro documentation"
        ]
      },
      {
        "slug": "getting-started",
        "title": "快速开始",
        "navTitle": "快速开始",
        "order": 2,
        "purpose": "Install the project and complete the first useful workflow.",
        "targetKeywords": [
          "astro getting started",
          "astro tutorial",
          "astro documentation"
        ]
      },
      {
        "slug": "core-concepts",
        "title": "核心概念",
        "navTitle": "核心概念",
        "order": 3,
        "purpose": "Explain the vocabulary and mental model behind the project.",
        "targetKeywords": [
          "astro core concepts",
          "astro tutorial",
          "astro documentation"
        ]
      },
      {
        "slug": "installation",
        "title": "安装",
        "navTitle": "安装",
        "order": 4,
        "purpose": "Cover supported runtimes, package managers, and environment setup.",
        "targetKeywords": [
          "astro installation",
          "astro tutorial",
          "astro documentation"
        ]
      },
      {
        "slug": "configuration",
        "title": "配置",
        "navTitle": "配置",
        "order": 5,
        "purpose": "Document configuration files, flags, and common presets.",
        "targetKeywords": [
          "astro configuration",
          "astro tutorial",
          "astro documentation"
        ]
      },
      {
        "slug": "tutorials",
        "title": "教程",
        "navTitle": "教程",
        "order": 6,
        "purpose": "Walk through practical tasks from beginner to intermediate level.",
        "targetKeywords": [
          "astro tutorials",
          "astro tutorial",
          "astro documentation"
        ]
      },
      {
        "slug": "examples",
        "title": "示例",
        "navTitle": "示例",
        "order": 7,
        "purpose": "Collect realistic examples readers can adapt.",
        "targetKeywords": [
          "astro examples",
          "astro tutorial",
          "astro documentation"
        ]
      },
      {
        "slug": "comparisons",
        "title": "对比",
        "navTitle": "对比",
        "order": 8,
        "purpose": "Compare alternatives and explain selection tradeoffs.",
        "targetKeywords": [
          "astro comparisons",
          "astro tutorial",
          "astro documentation"
        ]
      },
      {
        "slug": "faq",
        "title": "常见问题",
        "navTitle": "常见问题",
        "order": 9,
        "purpose": "Answer common adoption, migration, and troubleshooting questions.",
        "targetKeywords": [
          "astro faq",
          "astro tutorial",
          "astro documentation"
        ]
      },
      {
        "slug": "resources",
        "title": "资源",
        "navTitle": "资源",
        "order": 10,
        "purpose": "Link official docs, releases, examples, and source references.",
        "targetKeywords": [
          "astro resources",
          "astro tutorial",
          "astro documentation"
        ]
      }
    ]
  },
  "sources": [
    "https://github.com/withastro/astro"
  ]
}
